openbb_polymarket/__init__.py
openbb_polymarket/fetchers.py
openbb_polymarket/models.py
openbb_polymarket/polymarket_router.py
openbb_polymarket/provider.py
openbb_polymarket-0.1.0.dist-info/METADATA
openbb_polymarket-0.1.0.dist-info/WHEEL
openbb_polymarket-0.1.0.dist-info/entry_points.txt
openbb_polymarket-0.1.0.dist-info/RECORD
