Metadata-Version: 2.4
Name: openbb-polymarket
Version: 0.1.0
Summary: Polymarket provider + router extension for the OpenBB Platform
Requires-Python: >=3.10
Requires-Dist: httpx>=0.24
Requires-Dist: openbb-core>=1.5.0
